cs_manim/__init__.py
cs_manim/style.py
cs_manim/objects/__init__.py
cs_manim/objects/computer.py
cs_manim/objects/mobile_phone.py
cs_manim/objects/server.py
cs_manim-0.1.0.dist-info/licenses/LICENSE
cs_manim-0.1.0.dist-info/METADATA
cs_manim-0.1.0.dist-info/WHEEL
cs_manim-0.1.0.dist-info/top_level.txt
cs_manim-0.1.0.dist-info/RECORD
