Metadata-Version: 2.4
Name: cs-manim
Version: 0.1.0
Summary: Animations vidéo avec Manim pour expliquer les concepts techniques liés à l'informatique
Author-email: Pierre-Olivier Brillant <pierreolivierbrillant@gmail.com>
Maintainer-email: Pierre-Olivier Brillant <pierreolivierbrillant@gmail.com>
License: MIT
Project-URL: Homepage, https://github.com/PierreOlivierBrillant/cs-manim
Project-URL: Repository, https://github.com/PierreOlivierBrillant/cs-manim
Project-URL: Bug Tracker, https://github.com/PierreOlivierBrillant/cs-manim/issues
Keywords: manim,animation,education,computer-science,visualization,teaching
Classifier: Development Status :: 3 - Alpha
Classifier: Intended Audience :: Education
Classifier: Intended Audience :: Developers
Classifier: Programming Language :: Python :: 3
Classifier: Programming Language :: Python :: 3.10
Classifier: Programming Language :: Python :: 3.11
Classifier: Programming Language :: Python :: 3.12
Classifier: Programming Language :: Python :: 3.13
Classifier: Topic :: Education
Classifier: Topic :: Multimedia :: Graphics
Classifier: Topic :: Scientific/Engineering :: Visualization
Classifier: Topic :: Software Development :: Libraries :: Python Modules
Requires-Python: >=3.10
License-File: LICENSE
Requires-Dist: manim>=0.19.0
Provides-Extra: dev
Requires-Dist: black>=23.0.0; extra == "dev"
Requires-Dist: flake8>=6.0.0; extra == "dev"
Requires-Dist: flake8-pyproject>=1.2.0; extra == "dev"
Requires-Dist: mypy>=1.0.0; extra == "dev"
Requires-Dist: pytest>=7.0.0; extra == "dev"
Requires-Dist: pytest-cov>=4.0.0; extra == "dev"
Provides-Extra: docs
Requires-Dist: sphinx>=5.0.0; extra == "docs"
Requires-Dist: sphinx-rtd-theme>=1.0.0; extra == "docs"
Dynamic: license-file
